{
    "errorCode": 0,
    "id": 107,
    "userId": 1,
    "courseId": 1814,
    "courseTemplateId": 1074,
    "reference": "ISK-141052-107",
    "name": "张书斌",
    "phone": "13236563252",
    "status": 0,
    "noRefundDate": -1,
    "price": 1215.0,
    "type": 1,
    "lastModifyTime": 1410527583000,
    "createTime": 1410527583000,
    "enabled": 0,
    "actionList": [
        {
            "name": "offlineConfirm"
        },
        {
            "name": "offlineReject"
        },
        {
            "name": "offlineCancel"
        }
    ],
    "partnerId": 43,
    "course": {
        "errorCode": 0,
        "id": 1814,
        "courseName": "平面美工B",
        "courseTemplateId": 1074,
        "categoryId": 230,
        "locationId": 4,
        "circleId": 0,
        "partnerId": 43,
        "price": 1215.0,
        "originalPrice": 1280.0,
        "cashback": 45.0,
        "commission": 75.0,
        "status": 2,
        "lastModifyTime": 1410365708000,
        "createTime": 1409477177000,
        "enabled": 0,
        "marking": "爱会员完成在线支付可立减75元",
        "regPhone": "滚动开班，详情电询",
        "finishTime1": 2100,
        "startTime1": 1830,
        "startUponArrival": 0,
        "bookingType": 2,
        "cashbackDate": -1,
        "noRefundDate": -1,
        "popularity": 1997,
        "courseHourNum": 95,
        "classSize": "10人",
        "classType": 2,
        "schooltimeDay": 4,
        "schooltimeWeek": 3,
        "rating": 0.0,
        "bookingTotal": 0,
        "logoUrl": "http://logobucket.oss-cn-hangzhou.aliyuncs.com/43/logop43i1t1408527018907-13fce47ed92382a57cc554d138c74225.png",
        "wholeName": "南京瀚志文文化信息咨询有限公司",
        "instName": "南京瀚文教育培训中心",
        "partnerQualification": 1,
        "partnerRating": 0.0,
        "addressId": 73,
        "address": "南京市石鼓路33号环亚广场东方名苑B座10楼1010（新街口大洋百货后面）",
        "addressLat": 0.0,
        "addressLng": 0.0,
        "regAddressId": 73,
        "regAddress": "南京市石鼓路33号环亚广场东方名苑B座10楼1010（新街口大洋百货后面）",
        "regAddressLat": 0.0,
        "regAddressLng": 0.0,
        "categoryRank": 0
    }
}